[
    {
        "nome": "PAULO",
        "sobrenome": "DOS SANTOS",
        "email": "pda.ambrosio@gmail.com",
        "hash": "$2b$05$7bKaK0ChbHUbxCJGyyjuke7AWSHqxf2vMWKlvmjXwE6r.SYH6YddG"
    },
    {
        "nome": "MATHEUS BARCELLOS",
        "sobrenome": "STEGLICH",
        "email": "matheusbms951@gmail.com",
        "hash": "$2b$05$MWAeVy.kODofUOimeUSQmud7Ug/Y.6Q5PAO0Y8JUb/zQV1tgQZY0i"
    },
    {
        "nome": "Priscila",
        "sobrenome": "Fenner",
        "email": "malsmals@hotmail.com",
        "hash": "$2b$05$1/IU1g0brhXsiFUOIrmQ8eO5OHccHS7Eu0rSCoRN09NQkC035WnB2"
    },
    {
        "nome": "teste",
        "sobrenome": "teste",
        "email": "teste@hotmail.com",
        "hash": "$2b$05$kK0mcElnq/EMXnTaPPtdOOsWUTOj.wHWpl563IA8V4uPyHazehzCC"
    }
]